ctfhub/__init__.py
ctfhub/main.py
ctfhub-0.0.1.dist-info/METADATA
ctfhub-0.0.1.dist-info/WHEEL
ctfhub-0.0.1.dist-info/top_level.txt
ctfhub-0.0.1.dist-info/RECORD
